{
  "totalProjects": 172,
  "totalDiscussions": 406,
  "byTrack": {
    "ai": 74,
    "hardtech": 10,
    "biotech": 6,
    "consumer": 8,
    "saas": 10,
    "semiconductor": 1,
    "other": 8,
    "robotics": 39,
    "aerospace": 6,
    "newenergy": 8,
    "fintech": 2
  },
  "byStage": {
    "angel": 9,
    "b+": 55,
    "seed": 51,
    "a": 21,
    "pre-seed": 8,
    "b": 7,
    "idea": 4,
    "a+": 6,
    "pre-a": 10,
    "c1": 1
  },
  "byCity": {
    "guangzhou": 1,
    "overseas": 74,
    "hangzhou": 12,
    "beijing": 32,
    "other": 26,
    "nanjing": 1,
    "unknown": 1,
    "shenzhen": 7,
    "shanghai": 10,
    "wuhan": 1,
    "xiamen": 3,
    "suzhou": 2,
    "chengdu": 2
  },
  "avgScore": 67.0,
  "lastUpdate": "2026-05-12"
}