{
  "totalProjects": 227,
  "totalDiscussions": 547,
  "byTrack": {
    "ai": 93,
    "hardtech": 15,
    "biotech": 10,
    "consumer": 10,
    "saas": 16,
    "semiconductor": 7,
    "other": 7,
    "robotics": 44,
    "aerospace": 10,
    "newenergy": 10,
    "fintech": 4,
    "ecommerce": 1
  },
  "byStage": {
    "angel": 18,
    "b+": 62,
    "seed": 68,
    "a": 30,
    "pre-seed": 13,
    "b": 7,
    "idea": 6,
    "a+": 8,
    "pre-a": 13,
    "c1": 1,
    "unknown": 1
  },
  "byCity": {
    "guangzhou": 1,
    "overseas": 93,
    "hangzhou": 14,
    "beijing": 41,
    "other": 45,
    "nanjing": 1,
    "unknown": 1,
    "shenzhen": 10,
    "shanghai": 11,
    "wuhan": 1,
    "xiamen": 3,
    "suzhou": 3,
    "chengdu": 1,
    "changzhou": 1,
    "chongqing": 1
  },
  "avgScore": 67.3,
  "lastUpdate": "2026-05-20"
}